gewv_sides_client/__init__.py
gewv_sides_client/api_client.py
gewv_sides_client/configuration.py
gewv_sides_client/exceptions.py
gewv_sides_client/model_utils.py
gewv_sides_client/rest.py
gewv_sides_client/api/__init__.py
gewv_sides_client/api/analytics_api.py
gewv_sides_client/api/applications_api.py
gewv_sides_client/api/auth_api.py
gewv_sides_client/api/boxes_api.py
gewv_sides_client/api/buildings_api.py
gewv_sides_client/api/configurations_api.py
gewv_sides_client/api/contacts_api.py
gewv_sides_client/api/devices_api.py
gewv_sides_client/api/fieldtest_api.py
gewv_sides_client/api/fieldtests_api.py
gewv_sides_client/api/meters_api.py
gewv_sides_client/api/users_api.py
gewv_sides_client/apis/__init__.py
gewv_sides_client/model/__init__.py
gewv_sides_client/model/array_of_boxes.py
gewv_sides_client/model/array_of_buildings.py
gewv_sides_client/model/array_of_contacts.py
gewv_sides_client/model/array_of_devices.py
gewv_sides_client/model/array_of_fieldtests.py
gewv_sides_client/model/array_of_logs.py
gewv_sides_client/model/array_of_measur_services.py
gewv_sides_client/model/array_of_readings.py
gewv_sides_client/model/box.py
gewv_sides_client/model/box_all_of.py
gewv_sides_client/model/box_prototype.py
gewv_sides_client/model/building.py
gewv_sides_client/model/contact.py
gewv_sides_client/model/device.py
gewv_sides_client/model/energy_type.py
gewv_sides_client/model/fieldtest.py
gewv_sides_client/model/id.py
gewv_sides_client/model/inline_object.py
gewv_sides_client/model/inline_object1.py
gewv_sides_client/model/inline_object2.py
gewv_sides_client/model/inline_object3.py
gewv_sides_client/model/inline_object4.py
gewv_sides_client/model/inline_object5.py
gewv_sides_client/model/inline_object6.py
gewv_sides_client/model/log.py
gewv_sides_client/model/log_all_of.py
gewv_sides_client/model/log_level.py
gewv_sides_client/model/log_prototype.py
gewv_sides_client/model/measur_service.py
gewv_sides_client/model/measur_service_all_of.py
gewv_sides_client-1.0.1.dist-info/METADATA
gewv_sides_client-1.0.1.dist-info/WHEEL
gewv_sides_client-1.0.1.dist-info/top_level.txt
gewv_sides_client-1.0.1.dist-info/RECORD
