Metadata-Version: 2.1
Name: gewv-sides-client
Version: 1.0.1
Summary: The api of the tek ekg boxes and field controller.
Home-page: UNKNOWN
Author: OpenAPI Generator community
Author-email: team@openapitools.org
License: UNKNOWN
Keywords: OpenAPI,OpenAPI-Generator,The api of the tek ekg boxes and field controller.
Platform: UNKNOWN
Requires-Python: >=3.6
Requires-Dist: urllib3 (>=1.25.3)
Requires-Dist: python-dateutil
